LabIFSC/__init__.py
LabIFSC/geral.py
LabIFSC/grafico.py
LabIFSC/lista_de_unidades.py
LabIFSC/matematica.py
LabIFSC/medida.py
LabIFSC/tabela.py
LabIFSC/unidade.py
LabIFSC-0.1.13.dist-info/LICENSE
LabIFSC-0.1.13.dist-info/METADATA
LabIFSC-0.1.13.dist-info/WHEEL
LabIFSC-0.1.13.dist-info/top_level.txt
LabIFSC-0.1.13.dist-info/RECORD
