Metadata-Version: 2.1
Name: LabIFSC
Version: 0.1.13
Summary: Uma biblioteca para automatizar tarefas ligadas às disciplinas de laboratório de física do IFSC-USP (Python 2 e Python 3)
Home-page: https://github.com/gjvnq/LabIFSC
Author: Gabriel Queiroz
Author-email: gabrieljvnq@gmail.com
License: UNKNOWN
Keywords: uncertainty propagation,unit conversion
Platform: UNKNOWN
Classifier: Programming Language :: Python :: 2
Classifier: Programming Language :: Python :: 3
Classifier: License :: OSI Approved :: MIT License
Classifier: Operating System :: OS Independent
Classifier: Framework :: tox
Classifier: Intended Audience :: Education
Classifier: Natural Language :: Portuguese (Brazilian)
Classifier: Topic :: Scientific/Engineering
Classifier: Topic :: Scientific/Engineering :: Physics
Classifier: Topic :: Utilities
